MANIFEST.in
setup.py
django_f/__init__.py
django_f/asgi.py
django_f/settings.py
django_f/urls.py
django_f/wsgi.py
django_fonder/__init__.py
django_fonder/admin.py
django_fonder/apps.py
django_fonder/models.py
django_fonder/tests.py
django_fonder/views.py
django_fonder.egg-info/PKG-INFO
django_fonder.egg-info/SOURCES.txt
django_fonder.egg-info/dependency_links.txt
django_fonder.egg-info/requires.txt
django_fonder.egg-info/top_level.txt
django_fonder/management/commands/createapp.py
django_fonder/management/commands/find_model.py
django_fonder/management/commands/make_generator.py
django_fonder/migrations/__init__.py