Metadata-Version: 2.1
Name: django-fonder
Version: 1.0.0
Requires-Dist: Django>=3.0
